scull/__init__.py
scull/render/__init__.py
scull/render/pil.py
scull/render/tk.py
Scull-1.0.0.dist-info/LICENSE
Scull-1.0.0.dist-info/METADATA
Scull-1.0.0.dist-info/WHEEL
Scull-1.0.0.dist-info/top_level.txt
Scull-1.0.0.dist-info/RECORD
