Metadata-Version: 2.1
Name: Scull
Version: 1.0.0
Summary: A package that allows you to create skeleton animations
Author: GulgDev
Author-email: gulgdevs@yandex.com
Classifier: Programming Language :: Python :: 3
Classifier: License :: OSI Approved :: MIT License
Classifier: Operating System :: OS Independent
Requires-Python: >=3.6
License-File: LICENSE
